[
    {
        "ConfigFile": "server.cfg",
        "AutoMap": true,
        "ConfigType": "template",
        "ConfigFileTemplate": "./arma3/233780/AMP_server.cfg"
    },
    {
        "ConfigFile": "battleye/beserver{{ServerExecutable}}.cfg",
        "ConfigType": "kvp",
        "ConfigFormat": "{0} {1}",
        "Subsections": [
            {
                "Heading": "$root",
                "SettingMappings": {
                    "RConPassword": "$RemoteAdminPassword",
                    "RConPort": "$RCONPort",
                    "RConIP": "$ApplicationIPBinding"
                }
            }
        ]
    }
]