[
    {
        "ConfigFile":"server-data/server.cfg",
        "AutoMap":true,
        "ConfigType":"template",
        "ConfigFileTemplate":"./AMP_server.cfg"
    },
    {
        "ConfigFile":"server-data/user.cfg",
        "ConfigType":"kvp",
        "ConfigFormat":"{0}{1}",
        "Subsections":[
            {
                "Heading":"$root",
                "SettingMappings":{
                    "":"UserSettings"
                }
            }
        ]
    },
    {
        "ConfigFile":"server-data/admin.cfg",
        "ConfigType":"kvp",
        "ConfigFormat":"{0}{1}",
        "Subsections":[
            {
                "Heading":"$root",
                "SettingMappings":{
                    "":"Admins"
                }
            }
        ]
    }
]
