[
    {
        "Category": "Server Settings",
        "DefaultValue": "12871",
        "Description": "",
        "DisplayName": "Game Port",
        "EnumValues": {},
        "FieldName": "$GamePort",
        "Hidden": true,
        "IncludeInCommandLine": false,
        "InputType": "number",
        "IsFlagArgument": false,
        "Keywords": "",
        "ParamFieldName": "host"
    },
    {
        "Category": "Server Settings",
        "DefaultValue": "12881",
        "Description": "",
        "DisplayName": "Query Port",
        "EnumValues": {},
        "FieldName": "$QueryPort",
        "Hidden": true,
        "IncludeInCommandLine": false,
        "InputType": "number",
        "IsFlagArgument": false,
        "Keywords": "",
        "ParamFieldName": "queryport"
    },
    {
        "Category": "Server Settings",
        "DefaultValue": "My Hurtworld Server",
        "Description": "Server name as shown in the server browser",
        "DisplayName": "Server Name",
        "EnumValues": {},
        "FieldName": "servername",
        "IncludeInCommandLine": true,
        "InputType": "text",
        "IsFlagArgument": false,
        "Keywords": "name",
        "ParamFieldName": "servername",
        "SkipIfEmpty": true
    },
    {
        "Category": "Server Settings",
        "DefaultValue": "20",
        "Description": "Maximum number of players that may connect to the server",
        "DisplayName": "Player Limit",
        "EnumValues": {},
        "FieldName": "$MaxUsers",
        "IncludeInCommandLine": true,
        "InputType": "number",
        "IsFlagArgument": false,
        "Keywords": "maximum,players",
        "MinValue": 1,
        "ParamFieldName": "maxplayers",
        "SkipIfEmpty": true,
        "Suffix": "players"
    },
    {
        "Category": "Server Settings",
        "DefaultValue": "nullius",
        "Description": "Sets the map to load on the server",
        "DisplayName": "Map",
        "EnumValues": {},
        "FieldName": "map",
        "IncludeInCommandLine": false,
        "InputType": "text",
        "IsFlagArgument": false,
        "Keywords": "map",
        "ParamFieldName": "map",
        "Placeholder": "nullius"
    },
    {
        "Category": "Server Settings",
        "DefaultValue": "0",
        "Description": "If enabled, creative mode will apply (free build)",
        "DisplayName": "Enable Creative Mode",
        "EnumValues": {
            "False": "0",
            "True": "1"
        },
        "FieldName": "creativemode",
        "IncludeInCommandLine": true,
        "InputType": "checkbox",
        "IsFlagArgument": false,
        "Keywords": "creative,mode",
        "ParamFieldName": "creativemode"
    },
    {
        "Category": "Server Settings",
        "DefaultValue": "",
        "Description": "Steam64 ID of server admin. [Find Steam64 IDs](https://steamidfinder.com/)",
        "DisplayName": "Add Admin",
        "EnumValues": {},
        "FieldName": "addadmin",
        "IncludeInCommandLine": true,
        "InputType": "number",
        "IsFlagArgument": false,
        "Keywords": "admin",
        "ParamFieldName": "addadmin",
        "Placeholder": "58673958674589375",
        "SkipIfEmpty": true
    },
    {
        "Category": "Server Settings",
        "DefaultValue": "false",
        "Description": "If enabled, auto-installs uMod when the server is updated",
        "DisplayName": "Install uMod",
        "EnumValues": {
            "False": "false",
            "True": "true"
        },
        "FieldName": "uMod",
        "IncludeInCommandLine": false,
        "InputType": "checkbox",
        "IsFlagArgument": false,
        "Keywords": "install,umod",
        "ParamFieldName": "uMod"
    },
    {
        "Category": "Server Settings",
        "DefaultValue": "",
        "Description": "Space-separated list of Steam Workshop mod IDs to load on the server",
        "DisplayName": "Load Steam Workshop Mods",
        "EnumValues": {},
        "FieldName": "loadmod",
        "IncludeInCommandLine": true,
        "InputType": "text",
        "IsFlagArgument": false,
        "Keywords": "mods",
        "ParamFieldName": "loadmod",
        "Placeholder": "714026119 704019543",
        "SkipIfEmpty": true
    },
    {
        "Category": "Server Settings",
        "DefaultValue": "1",
        "Description": "If enabled, server wipe will be enabled",
        "DisplayName": "Enable Autowipe",
        "EnumValues": {
            "False": "0",
            "True": "1"
        },
        "FieldName": "autowipe",
        "IncludeInCommandLine": true,
        "InputType": "checkbox",
        "IsFlagArgument": false,
        "Keywords": "autowipe,wipe",
        "ParamFieldName": "autowipe"
    },
    {
        "Category": "Server Settings",
        "DefaultValue": "1209600",
        "Description": "Sets the server wipe schedule, as shown in the server browser. A negative number will show no wipe. Needs wipe enabled to work",
        "DisplayName": "Wipe Interval",
        "EnumValues": {},
        "FieldName": "wipeinterval",
        "IncludeInCommandLine": true,
        "InputType": "number",
        "IsFlagArgument": false,
        "Keywords": "wipe,interval,schedule",
        "ParamFieldName": "wipeinterval",
        "Placeholder": "1209600",
        "SkipIfEmpty": true,
        "Suffix": "seconds"
    },
    {
        "Category": "Server Settings",
        "DefaultValue": "",
        "Description": "Sets the player loot mode. Note: Alternate loot modes are experimental and may not work properly",
        "DisplayName": "Player Loot Mode",
        "EnumValues": {
            "": "Drop everything (default)",
            "1": "Drop backpack contents only",
            "2": "Drop backpack and one random item",
            "3": "Drop backpack and two random items",
            "4": "Drop backpack and three random items",
            "5": "Drop nothing",
            "6": "Destroy everything"
        },
        "FieldName": "playerlootmode",
        "IncludeInCommandLine": true,
        "InputType": "enum",
        "IsFlagArgument": false,
        "Keywords": "player,loot",
        "ParamFieldName": "playerlootmode",
        "SkipIfEmpty": true
    },
    {
        "Category": "Server Settings",
        "DefaultValue": "1",
        "Description": "If enabled, server will be autosaved",
        "DisplayName": "Enable Autosave",
        "EnumValues": {
            "False": "0",
            "True": "1"
        },
        "FieldName": "autosaveenabled",
        "IncludeInCommandLine": true,
        "InputType": "checkbox",
        "IsFlagArgument": false,
        "Keywords": "autosave",
        "ParamFieldName": "autosaveenabled"
    },
    {
        "Category": "Server Settings",
        "DefaultValue": "7200",
        "Description": "Sets how often the autosave should be backed up. Specify -1 to disable backup",
        "DisplayName": "Auto Backup Interval",
        "EnumValues": {},
        "FieldName": "autobackupinterval",
        "IncludeInCommandLine": true,
        "InputType": "number",
        "IsFlagArgument": false,
        "Keywords": "backup,interval",
        "ParamFieldName": "autobackupinterval",
        "Placeholder": "7200",
        "SkipIfEmpty": true,
        "Suffix": "seconds"
    },
    {
        "Category": "Server Settings",
        "DefaultValue": "1",
        "Description": "If enabled, structures will decay",
        "DisplayName": "Enable Structure Decay",
        "EnumValues": {
            "False": "0",
            "True": "1"
        },
        "FieldName": "structuredecayenabled",
        "IncludeInCommandLine": true,
        "InputType": "checkbox",
        "IsFlagArgument": false,
        "Keywords": "structure,decay",
        "ParamFieldName": "structuredecayenabled"
    },
    {
        "Category": "Server Settings",
        "DefaultValue": "600",
        "Description": "Sets how often a structure will be damaged by decay. Low values may have a performance impact",
        "DisplayName": "Structure Decay Frequency",
        "EnumValues": {},
        "FieldName": "structuredecayfrequency",
        "IncludeInCommandLine": true,
        "InputType": "number",
        "IsFlagArgument": false,
        "Keywords": "structure,decay,frequency",
        "ParamFieldName": "structuredecayfrequency",
        "Placeholder": "600",
        "SkipIfEmpty": true
    },
    {
        "Category": "Server Settings",
        "DefaultValue": "5 10",
        "Description": "Sets how much damage occurs when a structure decays. Specify one value for a set damage amount, or specify two values for a range",
        "DisplayName": "Structure Decay Damage",
        "EnumValues": {},
        "FieldName": "structuredecaydamage",
        "IncludeInCommandLine": true,
        "InputType": "text",
        "IsFlagArgument": false,
        "Keywords": "structure,decay,damage",
        "ParamFieldName": "structuredecaydamage",
        "Placeholder": "5 10",
        "SkipIfEmpty": true
    },
    {
        "Category": "Server Settings",
        "DefaultValue": "86400",
        "Description": "Sets how long a structure must be both unclaimed and unmodified, before it begins to decay",
        "DisplayName": "Structure Decay Start Time",
        "EnumValues": {},
        "FieldName": "structuredecaymodifytime",
        "IncludeInCommandLine": true,
        "InputType": "number",
        "IsFlagArgument": false,
        "Keywords": "structure,decay,modify,time",
        "ParamFieldName": "structuredecaymodifytime",
        "Placeholder": "86400",
        "SkipIfEmpty": true
    },
    {
        "Category": "Server Settings",
        "DefaultValue": "0",
        "Description": "If enabled, connection and disconnection messages will be displayed",
        "DisplayName": "Display Connection/Disconnection Messages",
        "EnumValues": {
            "False": "0",
            "True": "1"
        },
        "FieldName": "chatconnectionmessagesenabled",
        "IncludeInCommandLine": true,
        "InputType": "checkbox",
        "IsFlagArgument": false,
        "Keywords": "connection,disconnection,message",
        "ParamFieldName": "chatconnectionmessagesenabled"
    },
    {
        "Category": "Server Settings",
        "DefaultValue": "0",
        "Description": "If enabled, death messages will be displayed",
        "DisplayName": "Display Death Messages",
        "EnumValues": {
            "False": "0",
            "True": "1"
        },
        "FieldName": "chatdeathmessagesenabled",
        "IncludeInCommandLine": true,
        "InputType": "checkbox",
        "IsFlagArgument": false,
        "Keywords": "death,message",
        "ParamFieldName": "chatdeathmessagesenabled"
    },
    {
        "Category": "Server Settings",
        "DefaultValue": "200",
        "Description": "Sets the chat spam filter threshold. Lower values mean players will be muted sooner",
        "DisplayName": "Chat Spam Filter Threshold",
        "EnumValues": {},
        "FieldName": "chatspambudget",
        "IncludeInCommandLine": true,
        "InputType": "number",
        "IsFlagArgument": false,
        "Keywords": "chat,spam,filter",
        "ParamFieldName": "chatspambudget",
        "Placeholder": "200",
        "SkipIfEmpty": true
    },
    {
        "Category": "Server Settings",
        "DefaultValue": "20",
        "Description": "Sets how much time spawners can take",
        "DisplayName": "Spawner Time",
        "EnumValues": {},
        "FieldName": "spawnercellupdatesperframe",
        "IncludeInCommandLine": true,
        "InputType": "number",
        "IsFlagArgument": false,
        "Keywords": "spawner,time",
        "ParamFieldName": "spawnercellupdatesperframe",
        "Placeholder": "20",
        "SkipIfEmpty": true
    },
    {
        "Category": "Server Settings",
        "DefaultValue": "7200",
        "Description": "Sets the time a full ownership stake will take to deauthorise",
        "DisplayName": "Stake Deauthorise Time",
        "EnumValues": {},
        "FieldName": "stakedeauthtime",
        "IncludeInCommandLine": true,
        "InputType": "number",
        "IsFlagArgument": false,
        "Keywords": "stake,deauthorise",
        "ParamFieldName": "stakedeauthtime",
        "Placeholder": "7200",
        "SkipIfEmpty": true,
        "Suffix": "seconds"
    },
    {
        "Category": "Server Settings",
        "DefaultValue": "100",
        "Description": "Sets the target FPS for the server. Specify -1 for unlimited (not recommended)",
        "DisplayName": "Target FPS",
        "EnumValues": {},
        "FieldName": "targetfps",
        "IncludeInCommandLine": true,
        "InputType": "number",
        "IsFlagArgument": false,
        "Keywords": "target,fps",
        "ParamFieldName": "targetfps",
        "Placeholder": "100",
        "SkipIfEmpty": true
    },
    {
        "Category": "Server Settings",
        "DefaultValue": "100",
        "Description": "Sets how many resources the Load Balancer can use per frame",
        "DisplayName": "Load Balancer Resources",
        "EnumValues": {},
        "FieldName": "loadbalancerframebudget",
        "IncludeInCommandLine": true,
        "InputType": "number",
        "IsFlagArgument": false,
        "Keywords": "load,balancer,resources",
        "ParamFieldName": "loadbalancerframebudget",
        "Placeholder": "100",
        "SkipIfEmpty": true
    },
    {
        "Category": "Server Settings",
        "DefaultValue": "0",
        "Description": "If enabled, allows monitoring of the Load Balancer (view using \"dumploadbalancer\" command). Do not leave this enabled, as it has significant overhead",
        "DisplayName": "Enable Load Balancer Monitoring",
        "EnumValues": {
            "False": "0",
            "True": "1"
        },
        "FieldName": "monitorloadbalancer",
        "IncludeInCommandLine": true,
        "InputType": "checkbox",
        "IsFlagArgument": false,
        "Keywords": "monitor,load,balancer",
        "ParamFieldName": "monitorloadbalancer"
    }
]