[
    {
        "ConfigFile": "server.properties",
        "ConfigType": "kvp",
        "ConfigFormat": "{0}{1}",
        "Importable": "true",
        "Subsections": [
            {
                "Heading": "$root",
                "SettingMappings": {
                    "language=": "language",
                    "motd=": "motd",
                    "server-port=": "$ServerPortv4",
                    "server-portv6=": "$ServerPortv6",
                    "enable-ipv6=": "enable-ipv6",
                    "white-list=": "white-list",
                    "max-players=": "$MaxUsers",
                    "gamemode=": "gamemode",
                    "force-gamemode=": "force-gamemode",
                    "hardcore=": "hardcore",
                    "pvp=": "pvp",
                    "difficulty=": "difficulty",
                    "generator-settings=": "generator-settings",
                    "level-name=": "level-name",
                    "level-seed=": "level-seed",
                    "level-type=": "level-type",
                    "enable-query=": "enable-query",
                    "auto-save=": "auto-save",
                    "view-distance=": "view-distance",
                    "xbox-auth=": "xbox-auth",
                    "": "UserSettings"
                }
            }
        ]
    }
]