[
    {
        "DisplayName": "Server Name",
        "Category": "Server Settings",
        "Description": "The name displayed in server browser.",
        "Keywords": "server,name",
        "FieldName": "ServerName",
        "InputType": "text",
        "IsFlagArgument": false,
        "ParamFieldName": "ServerName",
        "IncludeInCommandLine": true,
        "DefaultValue": "My Renown Server",
        "Placeholder": "My Renown Server",
        "Suffix": "",
        "Hidden": false,
        "SkipIfEmpty": false,
        "EnumValues": {}
    },
    {
        "DisplayName": "Max Players",
        "Category": "Server Settings",
        "Description": "Max number of players.",
        "Keywords": "max,players",
        "FieldName": "MaxPlayers",
        "InputType": "number",
        "IsFlagArgument": false,
        "ParamFieldName": "MaxPlayers",
        "IncludeInCommandLine": true,
        "DefaultValue": "40",
        "Placeholder": "40",
        "Suffix": "",
        "Hidden": false,
        "SkipIfEmpty": false,
        "EnumValues": {}
    },
    {
        "DisplayName": "Region",
        "Category": "Server Settings",
        "Description": "Where your server is hosted.",
        "Keywords": "region",
        "FieldName": "Region",
        "InputType": "enum",
        "IsFlagArgument": false,
        "ParamFieldName": "Region",
        "IncludeInCommandLine": true,
        "DefaultValue": "US Central",
        "Placeholder": "US Central",
        "Suffix": "",
        "Hidden": false,
        "SkipIfEmpty": false,
        "EnumValues": {
            "US East": "US East",
            "US West": "US West",
            "US Central": "US Central",
            "Europe": "Europe",
            "South America": "South America",
            "Asia": "Asia",
            "Oceania": "Oceania"
        }
    },
    {
        "DisplayName": "MOTD",
        "Category": "Server Settings",
        "Description": "Message of the Day shown to players when they join.",
        "Keywords": "motd",
        "FieldName": "MOTD",
        "InputType": "text",
        "IsFlagArgument": false,
        "ParamFieldName": "MOTD",
        "IncludeInCommandLine": true,
        "DefaultValue": "Welcome to our Renown server!",
        "Placeholder": "Welcome to our Renown server!",
        "Suffix": "",
        "Hidden": false,
        "SkipIfEmpty": false,
        "EnumValues": {}
    },
    {
        "DisplayName": "EOS Client ID",
        "Category": "Server Settings",
        "Description": "EOS Client ID",
        "Keywords": "eos,client,id",
        "FieldName": "EOS Client ID",
        "InputType": "text",
        "IsFlagArgument": false,
        "ParamFieldName": "EOS Client ID",
        "IncludeInCommandLine": true,
        "DefaultValue": "",
        "Placeholder": "",
        "Suffix": "",
        "Hidden": true,
        "SkipIfEmpty": false,
        "EnumValues": {}
    },
    {
        "DisplayName": "EOS Client Secret",
        "Category": "Server Settings",
        "Description": "EOS Client Secret",
        "Keywords": "eos,client,secret",
        "FieldName": "EOS Client Secret",
        "InputType": "text",
        "IsFlagArgument": false,
        "ParamFieldName": "EOS Client Secret",
        "IncludeInCommandLine": true,
        "DefaultValue": "",
        "Placeholder": "",
        "Suffix": "",
        "Hidden": true,
        "SkipIfEmpty": false,
        "EnumValues": {}
    },
    {
        "DisplayName": "Map Rotation",
        "Category": "Server Settings",
        "Description": "Map Rotation",
        "Keywords": "map,rotation",
        "FieldName": "Map Rotation",
        "InputType": "text",
        "IsFlagArgument": false,
        "ParamFieldName": "Map Rotation",
        "IncludeInCommandLine": true,
        "DefaultValue": "",
        "Placeholder": "",
        "Suffix": "",
        "Hidden": false,
        "SkipIfEmpty": false,
        "EnumValues": {}
    }
]