[
    {
        "DisplayName": "Room Name",
        "Category": "Snapshot VR:stadia_controller",
        "Subcategory": "Server:dns:1",
        "Description": "Sets the name of the server room",
        "Keywords": "server,room,name,roomname",
        "FieldName": "roomname",
        "InputType": "text",
        "ParamFieldName": "roomname",
        "IncludeInCommandLine": true,
        "DefaultValue": "AMP Powered Snapshot VR Server",
        "Required": true,
        "EnumValues": {}
    },
    {
        "DisplayName": "Room Password",
        "Category": "Snapshot VR:stadia_controller",
        "Subcategory": "Server:dns:1",
        "Description": "Sets the password required to connect to the room",
        "Keywords": "server,room,password",
        "FieldName": "password",
        "InputType": "password",
        "ParamFieldName": "password",
        "IncludeInCommandLine": true,
        "SkipIfEmpty": true,
        "DefaultValue": "",
        "EnumValues": {}
    },
    {
        "DisplayName": "Hit Detection Mode",
        "Category": "Snapshot VR:stadia_controller",
        "Subcategory": "Server:dns:1",
        "Description": "Sets the hit detection mode",
        "Keywords": "hit,detection,mode,hitdetectionmode",
        "FieldName": "hitdetectionmode",
        "InputType": "enum",
        "ParamFieldName": "hitdetectionmode",
        "IncludeInCommandLine": true,
        "DefaultValue": "witness",
        "EnumValues": {
            "witness": "Witness/classic (default)",
            "authoritative": "Authoritative/improved"
        }
    }
]