[
    {
        "UpdateStageName": "Delete Log",
        "UpdateSourcePlatform": "Linux",
        "UpdateSource": "Executable",
        "UpdateSourceData": "/bin/bash",
        "UpdateSourceArgs": "-c \"rm -f \\\"{{$FullBaseDir}}latest-log.txt\\\" >/dev/null 2>&1\"",
        "SkipOnFailure": true
    },
    {
        "UpdateStageName": "Delete Log",
        "UpdateSourcePlatform": "Windows",
        "UpdateSource": "Executable",
        "UpdateSourceData": "powershell.exe",
        "UpdateSourceArgs": "-NoProfile -Command \"Remove-Item -Path \\\"{{$FullBaseDir}}latest-log.txt\\\" -Force -ErrorAction SilentlyContinue | Out-Null\"",
        "SkipOnFailure": true
    }
]