[
    {
        "Category": "Vintage Story:stadia_controller",
        "Description": "",
        "DisplayName": "Port",
        "EnumValues": {},
        "FieldName": "$ServerPort",
        "Hidden": true,
        "IncludeInCommandLine": false,
        "InputType": "number",
        "IsFlagArgument": false,
        "Keywords": "",
        "ParamFieldName": "$.Port",
        "Subcategory": "Server Settings:settings:1"
    },
    {
        "Category": "Vintage Story:stadia_controller",
        "DefaultValue": "true",
        "Description": "If enabled, the server will be added to the public server listing",
        "DisplayName": "Make Server Public",
        "EnumValues": {
            "False": "false",
            "True": "true"
        },
        "FieldName": "AdvertiseServer",
        "IncludeInCommandLine": false,
        "InputType": "checkbox",
        "IsFlagArgument": false,
        "Keywords": "public",
        "ParamFieldName": "$.AdvertiseServer",
        "Subcategory": "Server Settings:settings:1"
    },
    {
        "Category": "Vintage Story:stadia_controller",
        "DefaultValue": "Vintage Story Server - Powered by AMP",
        "Description": "Server name visible in the server list",
        "DisplayName": "Server Name",
        "EnumValues": {},
        "FieldName": "ServerName",
        "IncludeInCommandLine": false,
        "InputType": "text",
        "IsFlagArgument": false,
        "Keywords": "server,name",
        "ParamFieldName": "$.ServerName",
        "Subcategory": "Server Settings:settings:1"
    },
    {
        "Category": "Vintage Story:stadia_controller",
        "DefaultValue": "Welcome, {0}, may you survive well and prosper",
        "Description": "Welcome message when players join the server. Placeholder {0} will be replaced with the player's nickname",
        "DisplayName": "Welcome Message",
        "EnumValues": {},
        "FieldName": "WelcomeMessage",
        "IncludeInCommandLine": false,
        "InputType": "text",
        "IsFlagArgument": false,
        "Keywords": "welcome,message,motd",
        "ParamFieldName": "$.WelcomeMessage",
        "Subcategory": "Server Settings:settings:1"
    },
    {
        "Category": "Vintage Story:stadia_controller",
        "DefaultValue": "16",
        "Description": "Maximum number of players that may connect to the server",
        "DisplayName": "Player Limit",
        "EnumValues": {},
        "FieldName": "$MaxUsers",
        "IncludeInCommandLine": false,
        "InputType": "number",
        "IsFlagArgument": false,
        "Keywords": "players,limit",
        "MinValue": 1,
        "ParamFieldName": "$.MaxClients",
        "Subcategory": "Server Settings:settings:1",
        "Suffix": "players"
    },
    {
        "Category": "Vintage Story:stadia_controller",
        "DefaultValue": "false",
        "Description": "If enabled, only whitelisted players can join the server",
        "DisplayName": "Enable Whitelist",
        "EnumValues": {
            "False": "false",
            "True": "true"
        },
        "FieldName": "OnlyWhitelisted",
        "IncludeInCommandLine": false,
        "InputType": "checkbox",
        "IsFlagArgument": false,
        "Keywords": "whitelist",
        "ParamFieldName": "$.OnlyWhitelisted",
        "Subcategory": "Server Settings:settings:1"
    },
    {
        "Category": "Vintage Story:stadia_controller",
        "DefaultValue": "true",
        "Description": "If enabled, players can hit other players",
        "DisplayName": "Allow PvP",
        "EnumValues": {
            "False": "false",
            "True": "true"
        },
        "FieldName": "AllowPvP",
        "IncludeInCommandLine": false,
        "InputType": "checkbox",
        "IsFlagArgument": false,
        "Keywords": "pvp",
        "ParamFieldName": "$.AllowPvP",
        "Subcategory": "Server Settings:settings:1"
    },
    {
        "Category": "Vintage Story:stadia_controller",
        "DefaultValue": "false",
        "Description": "If enabled, the server will attempt to configure automatic port forwarding on a compatible router",
        "DisplayName": "Enable UPnP",
        "EnumValues": {
            "False": "false",
            "True": "true"
        },
        "FieldName": "Upnp",
        "IncludeInCommandLine": false,
        "InputType": "checkbox",
        "IsFlagArgument": false,
        "Keywords": "upnp",
        "ParamFieldName": "$.Upnp",
        "Subcategory": "Server Settings:settings:1"
    },
    {
        "Category": "Updates",
        "DefaultValue": "stable",
        "Description": "Sets the server release stream to install. An appropriate Server Version must also be set. NOTE: Update the server after changing this setting!",
        "DisplayName": "Server Release Stream",
        "EnumValues": {
            "pre": "Preview",
            "stable": "Stable (default)",
            "unstable": "Unstable"
        },
        "FieldName": "ServerReleaseStream",
        "IncludeInCommandLine": false,
        "InputType": "enum",
        "IsFlagArgument": false,
        "Keywords": "server,release,stream",
        "ParamFieldName": "ServerReleaseStream",
        "Subcategory": "Server Updates:build:-1"
    },
    {
        "Category": "Updates",
        "DefaultValue": "1.18.15",
        "Description": "Sets the server version to install, such as 1.18.5 or 1.19.0-pre.5. Minimum v1.18.8. NOTE: Update the server after changing this setting!",
        "DisplayName": "Server Version",
        "EnumValues": {},
        "FieldName": "ServerVersion",
        "IncludeInCommandLine": false,
        "InputType": "text",
        "IsFlagArgument": false,
        "Keywords": "server,version",
        "ParamFieldName": "ServerVersion",
        "Placeholder": "1.18.15 | 1.19.0-pre.5",
        "Required": true,
        "Subcategory": "Server Updates:build:-1"
    },
    {
        "Category": "Updates",
        "DefaultValue": "7.0.13",
        "Description": "Sets the [ASP.NET Core 7.0 version](https://dotnet.microsoft.com/en-us/download/dotnet/7.0) to install to run the server. NOTE: Update the server after switching versions!",
        "DisplayName": "Dotnet Version",
        "EnumValues": {},
        "FieldName": "DotnetVersion",
        "IncludeInCommandLine": false,
        "InputType": "text",
        "IsFlagArgument": false,
        "Keywords": "dotnet,version",
        "ParamFieldName": "DotnetVersion",
        "Placeholder": "7.0.13",
        "Required": true,
        "Subcategory": "Server Updates:build:-1"
    }
]